darglint2/__init__.py
darglint2/analysis/__init__.py
darglint2/analysis/abstract_callable_visitor.py
darglint2/analysis/analysis_helpers.py
darglint2/analysis/analysis_visitor.py
darglint2/analysis/argument_visitor.py
darglint2/analysis/assert_visitor.py
darglint2/analysis/function_and_method_visitor.py
darglint2/analysis/function_scoped_visitor.py
darglint2/analysis/raise_visitor.py
darglint2/analysis/return_visitor.py
darglint2/analysis/variable_visitor.py
darglint2/analysis/yield_visitor.py
darglint2/config.py
darglint2/custom_assert.py
darglint2/docstring/__init__.py
darglint2/docstring/base.py
darglint2/docstring/docstring.py
darglint2/docstring/google.py
darglint2/docstring/numpy.py
darglint2/docstring/sections.py
darglint2/docstring/sphinx.py
darglint2/docstring/style.py
darglint2/driver.py
darglint2/error_report.py
darglint2/errors.py
darglint2/flake8_entry.py
darglint2/function_description.py
darglint2/integrity_checker.py
darglint2/lex.py
darglint2/node.py
darglint2/parse/__init__.py
darglint2/parse/combinator.py
darglint2/parse/cyk.py
darglint2/parse/google.py
darglint2/parse/grammar.py
darglint2/parse/grammars/Makefile
darglint2/parse/grammars/__init__.py
darglint2/parse/grammars/google_arguments_section.bnf
darglint2/parse/grammars/google_arguments_section.py
darglint2/parse/grammars/google_base.bnf
darglint2/parse/grammars/google_long_description.bnf
darglint2/parse/grammars/google_long_description.py
darglint2/parse/grammars/google_raises_section.bnf
darglint2/parse/grammars/google_raises_section.py
darglint2/parse/grammars/google_returns_section.bnf
darglint2/parse/grammars/google_returns_section.py
darglint2/parse/grammars/google_returns_section_without_type.bnf
darglint2/parse/grammars/google_returns_section_without_type.py
darglint2/parse/grammars/google_short_description.bnf
darglint2/parse/grammars/google_short_description.py
darglint2/parse/grammars/google_types.bnf
darglint2/parse/grammars/google_yields_section.bnf
darglint2-1.8.2.dist-info/LICENSE.txt
darglint2-1.8.2.dist-info/METADATA
darglint2-1.8.2.dist-info/WHEEL
darglint2-1.8.2.dist-info/entry_points.txt
darglint2-1.8.2.dist-info/RECORD
